HISTORY.rst
LICENSE
MANIFEST.in
README.markdown
setup.cfg
setup.py
examples/simple.py
oembed/__init__.py
python_oembed.egg-info/PKG-INFO
python_oembed.egg-info/SOURCES.txt
python_oembed.egg-info/dependency_links.txt
python_oembed.egg-info/top_level.txt
test/test_net.py