Metadata-Version: 1.1
Name: python-oembed
Version: 0.2.4
Summary: OEmbed consumer library for Python
Home-page: http://github.com/abarmat/python-oembed
Author: Ariel Barmat
Author-email: abarmat@gmail.com
License: MIT
Keywords: oembed python api
Platform: UNKNOWN
Classifier: Development Status :: 4 - Beta
Classifier: License :: OSI Approved :: MIT License
Classifier: Programming Language :: Python
Classifier: Programming Language :: Python :: 2.5
Classifier: Programming Language :: Python :: 2.6
Classifier: Programming Language :: Python :: 3.4
